HyruleCompendium/__init__.py
HyruleCompendium-0.0.3.dist-info/LICENSE
HyruleCompendium-0.0.3.dist-info/METADATA
HyruleCompendium-0.0.3.dist-info/WHEEL
HyruleCompendium-0.0.3.dist-info/top_level.txt
HyruleCompendium-0.0.3.dist-info/RECORD
