Metadata-Version: 2.1
Name: HyruleCompendium
Version: 0.0.3
Summary: Python Wrapper for the Hyrule Compendium API
Home-page: https://github.com/Hyrule-Compendium-API/Hyrule-Compendium-python-client
Author: Shaunik Musukula
Author-email: shaunik.musukula@gmail.com
License: UNKNOWN
Platform: UNKNOWN
Classifier: Programming Language :: Python :: 3
Classifier: License :: OSI Approved :: MIT License
Classifier: Operating System :: OS Independent
Requires-Python: >=3.6
Requires-Dist: requests
